sseqs/__init__.py
sseqs/helper.cu
sseqs/msa.py
sseqs/msas.py
sseqs/sw.cu
sseqs/sw.py
sseqs/sw_affine.cu
sseqs/sw_affine_uint8.cu
sseqs/sw_backtrack_vram.cu
sseqs/sw_bind.cpp
sseqs/sw_linear.cu
sseqs/sw_profile.cu
sseqs/to_a3m.py
sseqs/utils.py
sseqs/xbit.cu
sseqs/xbit.py
sseqs/xbit_bind.cpp
sseqs-0.0.11.dist-info/licenses/LICENSE
sseqs-0.0.11.dist-info/METADATA
sseqs-0.0.11.dist-info/WHEEL
sseqs-0.0.11.dist-info/top_level.txt
sseqs-0.0.11.dist-info/RECORD
