Metadata-Version: 2.4
Name: sseqs
Version: 0.0.11
Summary: Simple MSA
Author: Alexander Mathiasen
License: MIT License
Keywords: sseqs
Classifier: Programming Language :: Python :: 3
Classifier: License :: OSI Approved :: MIT License
Classifier: Operating System :: OS Independent
Requires-Python: >=3.9
License-File: LICENSE
Requires-Dist: icecream
Requires-Dist: torch
Requires-Dist: numpy
Requires-Dist: tqdm
Requires-Dist: pqdm
Requires-Dist: matplotlib
Requires-Dist: ninja
Requires-Dist: pandas
Requires-Dist: ipywidgets
Requires-Dist: natsort
Requires-Dist: dill
Requires-Dist: uvicorn
Requires-Dist: python-multipart
Dynamic: license-file
